rustic_ai/ray/__init__.py
rustic_ai/ray/execution/__init__.py
rustic_ai/ray/execution/ray_agent_wrapper.py
rustic_ai/ray/execution/ray_exec_engine.py
rusticai_ray-1.0.0.dist-info/METADATA
rusticai_ray-1.0.0.dist-info/WHEEL
rusticai_ray-1.0.0.dist-info/RECORD
