Metadata-Version: 2.4
Name: rusticai-ray
Version: 1.0.0
Summary: Rustic AI execution engine running on Ray Cluster
License-Expression: Apache-2.0
Author: Dragonscale Industries Inc.
Author-email: dev@dragonscale.ai
Requires-Python: >=3.12,<3.13
Classifier: Programming Language :: Python :: 3
Classifier: Programming Language :: Python :: 3.12
Provides-Extra: test
Requires-Dist: opentelemetry-exporter-otlp (>=1.31.1,<2.0.0)
Requires-Dist: opentelemetry-exporter-otlp-proto-grpc (>=1.31.1,<2.0.0)
Requires-Dist: opentelemetry-sdk (>=1.31.1,<2.0.0)
Requires-Dist: ray[default] (>=2.44.1,<3.0.0)
Requires-Dist: rusticai-core (>=1.0.0,<1.1.0)
Project-URL: Homepage, https://www.rustic.ai/
Project-URL: Repository, https://github.com/rustic-ai/rustic-ai
Project-URL: Rustic AI Core, https://pypi.org/project/rusticai-core/
